injkt/__init__.py
injkt/__main__.py
injkt/bind.py
injkt/decorator.py
injkt/exceptions.py
injkt/injectable.py
injkt/injkt_lazy.py
injkt/injktor.py
injkt/meta.py
injkt-0.1.0.dist-info/METADATA
injkt-0.1.0.dist-info/WHEEL
injkt-0.1.0.dist-info/RECORD
