Metadata-Version: 2.1
Name: injkt
Version: 0.1.0
Summary: Dependency ~~injection~~ injktion
License: MIT
Author: CaffeineDuck
Author-email: hello@samrid.me
Requires-Python: >=3.10,<4.0
Classifier: License :: OSI Approved :: MIT License
Classifier: Programming Language :: Python :: 3
Classifier: Programming Language :: Python :: 3.10
Classifier: Programming Language :: Python :: 3.11
Classifier: Programming Language :: Python :: 3.12
